simpler_cli.py
simpler_cli-0.2.0.dist-info/METADATA
simpler_cli-0.2.0.dist-info/WHEEL
simpler_cli-0.2.0.dist-info/entry_points.txt
simpler_cli-0.2.0.dist-info/top_level.txt
simpler_cli-0.2.0.dist-info/RECORD
