Metadata-Version: 2.1
Name: simpler-cli
Version: 0.2.0
Summary: CLI for the simple ER package collection
Author-email: Philipp Schmurr <philipp.schmurr@kit.edu>
Maintainer-email: Philipp Schmurr <philipp.schmurr@kit.edu>
Project-URL: Homepage, https://github.com/Cpprentice/FAIRlead-model-extraction
Project-URL: Bug Reports, https://github.com/Cpprentice/FAIRlead-model-extraction/issues
Project-URL: Source, https://github.com/Cpprentice/FAIRlead-model-extraction
Keywords: entity-relationship-model,ER,extraction,model,cli,simpler
Classifier: Development Status :: 3 - Alpha
Classifier: Intended Audience :: Developers
Classifier: License :: OSI Approved :: MIT License
Classifier: Programming Language :: Python :: 3
Classifier: Programming Language :: Python :: 3.12
Classifier: Programming Language :: Python :: 3 :: Only
Requires-Python: >=3.12
Requires-Dist: simpler-core ==0.2.0
